geoglows/__init__.py
geoglows/_constants.py
geoglows/_download_decorators.py
geoglows/analyze.py
geoglows/bias.py
geoglows/data.py
geoglows/tables.py
geoglows/_plots/__init__.py
geoglows/_plots/format_tools.py
geoglows/_plots/plotly_bias_corrected.py
geoglows/_plots/plotly_forecasts.py
geoglows/_plots/plotly_helpers.py
geoglows/_plots/plotly_retrospective.py
geoglows/_plots/plots.py
geoglows-2.1.0.dist-info/licenses/LICENSE
geoglows-2.1.0.dist-info/METADATA
geoglows-2.1.0.dist-info/WHEEL
geoglows-2.1.0.dist-info/top_level.txt
geoglows-2.1.0.dist-info/RECORD
