Metadata-Version: 2.4
Name: geoglows
Version: 2.1.0
Summary: Package for accessing data from the GEOGLOWS Hydrological Model
Home-page: https://data.geoglows.org
Author: Riley Hales PhD
License: BSD 3-Clause Clear License
Project-URL: Homepage, https://data.geoglows.org
Project-URL: Documentation, https://geoglows.readthedocs.io
Project-URL: Source, https://github.com/geoglows/pygeoglows
Classifier: Development Status :: 5 - Production/Stable
Classifier: Programming Language :: Python :: 3
Classifier: Topic :: Scientific/Engineering :: Hydrology
Classifier: Topic :: Scientific/Engineering :: Visualization
Classifier: Intended Audience :: Science/Research
Classifier: License :: OSI Approved :: BSD License
Classifier: Natural Language :: English
Requires-Python: >=3.7.0
License-File: LICENSE
Requires-Dist: dask>=2022
Requires-Dist: fastparquet
Requires-Dist: requests
Requires-Dist: pandas>=1
Requires-Dist: plotly>=5
Requires-Dist: scipy>=1
Requires-Dist: s3fs>=2022
Requires-Dist: numpy>=1
Requires-Dist: hydrostats
Requires-Dist: HydroErr
Requires-Dist: xarray>=2025
Requires-Dist: zarr>=2
Dynamic: author
Dynamic: classifier
Dynamic: description
Dynamic: description-content-type
Dynamic: home-page
Dynamic: license
Dynamic: license-file
Dynamic: project-url
Dynamic: requires-dist
Dynamic: requires-python
Dynamic: summary
